Assignment 2_1/Assignment 2_1.srcs/sources_1/new/Decoder_Gate.v
`timescale 1ns / 1ps
//////////////////////////////////////////////////////////////////////////////////
// Company: FPGA & HDL
// Engineer: Oscar Osornio
// 
// Create Date: 07/02/2022 02:29:07 PM
// Design Name: Assignment 2
// Module Name: Decoder_Gate
// Project Name: 
// Target Devices: 
// Tool Versions: 
// Description: 
// 
// Dependencies: 
// 
// Revision:
// Revision 0.01 - File Created
// Additional Comments:
// 
//////////////////////////////////////////////////////////////////////////////////


module Decoder_Gate(
    input A, B, C, D,
    output zero, one, two, three, four, five, six, seven, eight,
                nine, ten, eleven, twelve, thirteen
    );
    
    wire A_not, B_not, C_not, D_not;
    
    not NOT1(A_not, A);
    not NOT2(B_not, B);
    not NOT3(C_not, C);
    not NOT4(D_not, D);
    
    and AND13(thirteen, A_not, B_not, C_not, D_not);
    and AND12(twelve, A_not, B_not, C_not, D);
    and AND11(eleven, A_not, B_not, C, D_not);
    and AND10(ten, A_not, B_not, C, D);
    and AND9(nine, A_not, B, C_not, D_not);
    and AND8(eight, A_not, B, C_not, D);
    and AND7(seven, A_not, B, C, D_not);
    and AND6(six, A_not, B, C, D);
    and AND5(five, A, B_not, C_not, D_not);
    and AND4(four, A, B_not, C, D_not);
    and AND3(three, A, B_not, C, D);
    and AND2(two, A, B, C_not, D_not);
    and AND1(one, A, B, C_not, D);
    and AND0(zero, A, B, C, D);
    
endmodule

Assignment 2_1/Assignment 2_1.srcs/sim_1/new/tb_gate.v
`timescale 1ns / 1ps
//////////////////////////////////////////////////////////////////////////////////
// Company: FPGA & HDL
// Engineer: Oscar Osornio
// 
// Create Date: 07/02/2022 05:08:52 PM
// Design Name: Assignment 2 Problem 1
// Module Name: tb_gate
// Project Name: 
// Target Devices: 
// Tool Versions: 
// Description: 
// 
// Dependencies: 
// 
// Revision:
// Revision 0.01 - File Created
// Additional Comments:
// 
//////////////////////////////////////////////////////////////////////////////////


module tb_gate();

    //declare test bench module variables 
    reg A_input, B_input, C_input, D_input;
    wire zero, one, two, three, four, five, six, seven, eight,
         nine, ten, eleven, twelve, thirteen;
         
    //instantiate the design module and connect to the testbench variables 
    Decoder_Gate instantiation(.A(A_input), .B(B_input), .C(C_input), .D(D_input), 
                               .zero(zero), .one(one), .two(two), .three(three), 
                               .four(four), .five(five), .six(six), .seven(seven), 
                               .eight(eight), .nine(nine), .ten(ten), .eleven(eleven), 
                               .twelve(twelve), .thirteen(thirteen));
                               
    initial
        begin
            $dumpfile("xyz.vcd");
            $dumpvars;
            
            //set stimulus to test the code 
            A_input = 0;
            B_input = 0;
            C_input = 0;
            D_input = 0;
            #160 $finish;
        end 
        
    //provide the toggling input (truth table)
    //this acts as the clock input 
    always #80 A_input = ~A_input;
    always #40 B_input = ~B_input;
    always #20 C_input = ~C_input;
    always #10 D_input = ~D_input;
    
    //display output if there's a change in input event 
    always @(A_input or B_input or C_input or D_input)
        $monitor("At TIME(in ns) = %t, input = %b%b%b%b, output = %b%b%b%b%b%b%b%b%b%b%b%b%b%b", 
                 $time, A_input, B_input, C_input, D_input, zero, one, two, three, 
                 four, five, six, seven, eight, nine, ten, eleven, twelve, thirteen);

endmodule

Assignment 2_1/Assignment 2_1.sim/sim_1/behav/xsim/xyz.vcd
$date
   Sat Jul  2 17:32:04 2022
$end
$version
  2022.1
$end
$timescale
  1ps
$end
$scope module tb_gate $end
$var reg 1 ! A_input $end
$var reg 1 " B_input $end
$var reg 1 # C_input $end
$var reg 1 $ D_input $end
$var wire 1 % zero $end
$var wire 1 & one $end
$var wire 1 ' two $end
$var wire 1 ( three $end
$var wire 1 ) four $end
$var wire 1 * five $end
$var wire 1 + six $end
$var wire 1 , seven $end
$var wire 1 - eight $end
$var wire 1 . nine $end
$var wire 1 / ten $end
$var wire 1 0 eleven $end
$var wire 1 1 twelve $end
$var wire 1 2 thirteen $end
$scope module instantiation $end
$var wire 1 3 A $end
$var wire 1 4 B $end
$var wire 1 5 C $end
$var wire 1 6 D $end
$var wire 1 % zero $end
$var wire 1 & one $end
$var wire 1 ' two $end
$var wire 1 ( three $end
$var wire 1 ) four $end
$var wire 1 * five $end
$var wire 1 + six $end
$var wire 1 , seven $end
$var wire 1 - eight $end
$var wire 1 . nine $end
$var wire 1 / ten $end
$var wire 1 0 eleven $end
$var wire 1 1 twelve $end
$var wire 1 2 thirteen $end
$var wire 1 7 A_not $end
$var wire 1 8 B_not $end
$var wire 1 9 C_not $end
$var wire 1 : D_not $end
$upscope $end
$upscope $end
$enddefinitions $end
#0
$dumpvars
0!
0"
0#
0$
0%
0&
0'
0(
0)
0*
0+
0,
0-
0.
0/
00
01
12
03
04
05
06
17
18
19
1:
$end
#10000
1$
0%
0&
0'
0(
0)
0*
0+
0,
0-
0.
0/
00
11
02
16
0:
#20000
1#
0$
0%
0&
0'
0(
0)
0*
0+
0,
0-
0.
0/
10
01
02
15
06
09
1:
#30000
1$
0%
0&
0'
0(
0)
0*
0+
0,
0-
0.
1/
00
01
02
16
0:
#40000
1"
0#
0$
0%
0&
0'
0(
0)
0*
0+
0,
0-
1.
0/
00
01
02
14
05
06
08
19
1:
#50000
1$
0%
0&
0'
0(
0)
0*
0+
0,
1-
0.
0/
00
01
02
16
0:
#60000
1#
0$
0%
0&
0'
0(
0)
0*
0+
1,
0-
0.
0/
00
01
02
15
06
09
1:
#70000
1$
0%
0&
0'
0(
0)
0*
1+
0,
0-
0.
0/
00
01
02
16
0:
#80000
1!
0"
0#
0$
0%
0&
0'
0(
0)
1*
0+
0,
0-
0.
0/
00
01
02
13
04
05
06
07
18
19
1:
#90000
1$
0%
0&
0'
0(
0)
0*
0+
0,
0-
0.
0/
00
01
02
16
0:
#100000
1#
0$
0%
0&
0'
0(
1)
0*
0+
0,
0-
0.
0/
00
01
02
15
06
09
1:
#110000
1$
0%
0&
0'
1(
0)
0*
0+
0,
0-
0.
0/
00
01
02
16
0:
#120000
1"
0#
0$
0%
0&
1'
0(
0)
0*
0+
0,
0-
0.
0/
00
01
02
14
05
06
08
19
1:
#130000
1$
0%
1&
0'
0(
0)
0*
0+
0,
0-
0.
0/
00
01
02
16
0:
#140000
1#
0$
0%
0&
0'
0(
0)
0*
0+
0,
0-
0.
0/
00
01
02
15
06
09
1:
#150000
1$
1%
0&
0'
0(
0)
0*
0+
0,
0-
0.
0/
00
01
02
16
0:
