Assignment 1_3/Assignment 1_3.srcs/sources_1/new/Circuit3.v
`timescale 1ns / 1ps
//////////////////////////////////////////////////////////////////////////////////
// Company: 
// Engineer: 
// 
// Create Date: 06/19/2022 09:56:01 PM
// Design Name: 
// Module Name: Circuit3
// Project Name: 
// Target Devices: 
// Tool Versions: 
// Description: 
// 
// Dependencies: 
// 
// Revision:
// Revision 0.01 - File Created
// Additional Comments:
// 
//////////////////////////////////////////////////////////////////////////////////


module Circuit3(
    input wire A, B, C, D,
    output reg f
    );
    
    always @(A or B or C or D)
        begin
        
            if (C == 1 && D == 0)
                begin
                    f = 1;
                end
            else if (B == 1 && D == 1)
                begin
                    f = 1;
                end
            else if (B == 0 && C == 0)
                begin
                    f = 1;
                end
            else
                begin
                    f = 0;
                end      
            
        end 
    
endmodule

Assignment 1_3/Assignment 1_3.srcs/sim_1/new/tb_Circuit3.v
`timescale 1ns / 1ps
//////////////////////////////////////////////////////////////////////////////////
// Company: 
// Engineer: 
// 
// Create Date: 06/19/2022 10:02:00 PM
// Design Name: 
// Module Name: tb_Circuit3
// Project Name: 
// Target Devices: 
// Tool Versions: 
// Description: 
// 
// Dependencies: 
// 
// Revision:
// Revision 0.01 - File Created
// Additional Comments:
// 
//////////////////////////////////////////////////////////////////////////////////


module tb_Circuit3(
    );
    
    //declare testbench variables 
    reg A_input, B_input, C_input, D_input;
    wire f_output;
    
    //instantiate the design module and connect to the testbench variables 
    Circuit3 instantiation(.A(A_input), .B(B_input), .C(C_input), 
                            .D(D_input), .f(f_output));
    
    initial
        begin
            $dumpfile("xyz.vcd");
            $dumpvars;
            
            //set stimulus to test the code 
            A_input = 0;
            B_input = 0;
            C_input = 0;
            D_input = 0;
            #200 $finish;
        end 
        
    //provide the toggling input (truth table)
    //this acts as the clock input 
    always #80 A_input = ~A_input;
    always #40 B_input = ~B_input;
    always #20 C_input = ~C_input;
    always #10 D_input = ~D_input;
    
    //display output if there's a change in input event 
    always @(A_input or B_input or C_input or D_input)
        $monitor("At TIME(in ns) = %t, A = %d B = %d C = %d D = %d f = %d",
                 $time, A_input, B_input, C_input, D_input, f_output);

    
endmodule

Assignment 1_3/Assignment 1_3.sim/sim_1/behav/xsim/xyz.vcd
$date
   Sun Jun 19 22:36:49 2022
$end
$version
  2022.1
$end
$timescale
  1ps
$end
$scope module tb_Circuit3 $end
$var reg 1 ! A_input $end
$var reg 1 " B_input $end
$var reg 1 # C_input $end
$var reg 1 $ D_input $end
$var wire 1 % f_output $end
$scope module instantiation $end
$var wire 1 & A $end
$var wire 1 ' B $end
$var wire 1 ( C $end
$var wire 1 ) D $end
$var reg 1 * f $end
$upscope $end
$upscope $end
$enddefinitions $end
#0
$dumpvars
0!
0"
0#
0$
1%
0&
0'
0(
0)
1*
$end
#10000
1$
1)
1*
#20000
1#
0$
1(
0)
1*
#30000
1$
0%
1)
0*
#40000
1"
0#
0$
1'
0(
0)
0*
#50000
1$
1%
1)
1*
#60000
1#
0$
1(
0)
1*
#70000
1$
1)
1*
#80000
1!
0"
0#
0$
1&
0'
0(
0)
1*
#90000
1$
1)
1*
#100000
1#
0$
1(
0)
1*
#110000
1$
0%
1)
0*
#120000
1"
0#
0$
1'
0(
0)
0*
#130000
1$
1%
1)
1*
#140000
1#
0$
1(
0)
1*
#150000
1$
1)
1*
#160000
0!
0"
0#
0$
0&
0'
0(
0)
1*
#170000
1$
1)
1*
#180000
1#
0$
1(
0)
1*
#190000
1$
0%
1)
0*
