Assignment 2_2/Assignment 2_2.srcs/sources_1/new/Arbiter FSM.v
`timescale 1ns / 1ps
//////////////////////////////////////////////////////////////////////////////////
// Company: FPGA & Verilog HDL
// Engineer: Oscar Osornio
// 
// Create Date: 07/01/2022 02:01:13 PM
// Design Name: Assignment 2 Problem 2
// Module Name: Arbiter FSM
// Project Name: 
// Target Devices: 
// Tool Versions: 
// Description: 
// 
// Dependencies: 
// 
// Revision:
// Revision 0.01 - File Created
// Additional Comments:
// 
//////////////////////////////////////////////////////////////////////////////////


module Arbiter_FSM(
    input wire [2:0] req,
    input wire reset, clock,
    output reg [2:0] gnt
    );
    
    always @(negedge clock, negedge reset)
        begin
            if (reset)
                gnt <= 3'b000;
            else
            begin
                case ({req})
                    3'b000: begin gnt <= 3'b001; end 
                    3'b001: begin gnt <= 3'b001; end 
                    3'b010: begin gnt <= 3'b010; end 
                    3'b011: begin gnt <= 3'b010; end 
                    3'b100: begin gnt <= 3'b100; end 
                    3'b101: begin gnt <= 3'b001; end 
                    3'b110: begin gnt <= 3'b100; end 
                    3'b111: begin gnt <= 3'b001; end
                endcase
            end
        end
endmodule

Assignment 2_2/Assignment 2_2.srcs/sim_1/new/tb_arbiter.v
`timescale 1ns / 1ps
//////////////////////////////////////////////////////////////////////////////////
// Company: FPGA & Verilog HDL
// Engineer: Oscar Osornio
// 
// Create Date: 07/02/2022 06:54:53 PM
// Design Name: Assignment 2 Problem 2
// Module Name: tb_arbiter
// Project Name: 
// Target Devices: 
// Tool Versions: 
// Description: 
// 
// Dependencies: 
// 
// Revision:
// Revision 0.01 - File Created
// Additional Comments:
// 
//////////////////////////////////////////////////////////////////////////////////


module tb_arbiter();

    //declare testbench variables 
    reg [2:0] req_input;
    reg clock_input, reset_input;
    wire [2:0] gnt_output;
    
    //instantiate the design module and connect to the testbench module variables 
    Arbiter_FSM instantiation(.req(req_input), .clock(clock_input), .reset(reset_input),
                              .gnt(gnt_output));
    
    //generate the clock
    initial
        begin
            clock_input = 1'b0;
            forever #1 clock_input = ~clock_input;
        end
    
    //generate the reset 
    initial
        begin
            reset_input = 1'b1;
            #10 
            reset_input = 1'b0;
       end
    
    initial
        begin
            $dumpfile("xyz.vcd");
            $dumpvars;
            
            //set stimulus to test the code 
            req_input = 3'b000; #20 
            req_input = 3'b001; #10 
            req_input = 3'b010; #10 
            req_input = 3'b011; #10 
            req_input = 3'b100; #10 
            req_input = 3'b101; #10 
            req_input = 3'b110; #10 
            req_input = 3'b111; #20 
            $finish;
        end 
        
    //display output if there's a change in input event 
    always @(req_input)
        $monitor("At TIME(in ns) = %t, req = %b, gnt = %b",
                 $time, req_input, gnt_output);

endmodule

Assignment 2_2/Assignment 2_2.sim/sim_1/behav/xsim/xyz.vcd
$date
   Sat Jul  2 19:51:55 2022
$end
$version
  2022.1
$end
$timescale
  1ps
$end
$scope module tb_arbiter $end
$var reg 3 ! req_input [2:0] $end
$var reg 1 " clock_input $end
$var reg 1 # reset_input $end
$var wire 3 $ gnt_output [2:0] $end
$scope module instantiation $end
$var wire 3 % req [2:0] $end
$var wire 1 & reset $end
$var wire 1 ' clock $end
$var reg 3 ( gnt [2:0] $end
$upscope $end
$upscope $end
$enddefinitions $end
#0
$dumpvars
b0 !
0"
1#
b0 $
b0 %
1&
0'
b0 (
$end
#1000
1"
1'
#2000
0"
0'
b0 (
#3000
1"
1'
#4000
0"
0'
b0 (
#5000
1"
1'
#6000
0"
0'
b0 (
#7000
1"
1'
#8000
0"
0'
b0 (
#9000
1"
1'
#10000
0"
0#
b1 $
0&
0'
b1 (
#11000
1"
1'
#12000
0"
0'
b1 (
#13000
1"
1'
#14000
0"
0'
b1 (
#15000
1"
1'
#16000
0"
0'
b1 (
#17000
1"
1'
#18000
0"
0'
b1 (
#19000
1"
1'
#20000
b1 !
0"
b1 %
0'
b1 (
#21000
1"
1'
#22000
0"
0'
b1 (
#23000
1"
1'
#24000
0"
0'
b1 (
#25000
1"
1'
#26000
0"
0'
b1 (
#27000
1"
1'
#28000
0"
0'
b1 (
#29000
1"
1'
#30000
b10 !
0"
b10 $
b10 %
0'
b10 (
#31000
1"
1'
#32000
0"
0'
b10 (
#33000
1"
1'
#34000
0"
0'
b10 (
#35000
1"
1'
#36000
0"
0'
b10 (
#37000
1"
1'
#38000
0"
0'
b10 (
#39000
1"
1'
#40000
b11 !
0"
b11 %
0'
b10 (
#41000
1"
1'
#42000
0"
0'
b10 (
#43000
1"
1'
#44000
0"
0'
b10 (
#45000
1"
1'
#46000
0"
0'
b10 (
#47000
1"
1'
#48000
0"
0'
b10 (
#49000
1"
1'
#50000
b100 !
0"
b100 $
b100 %
0'
b100 (
#51000
1"
1'
#52000
0"
0'
b100 (
#53000
1"
1'
#54000
0"
0'
b100 (
#55000
1"
1'
#56000
0"
0'
b100 (
#57000
1"
1'
#58000
0"
0'
b100 (
#59000
1"
1'
#60000
b101 !
0"
b1 $
b101 %
0'
b1 (
#61000
1"
1'
#62000
0"
0'
b1 (
#63000
1"
1'
#64000
0"
0'
b1 (
#65000
1"
1'
#66000
0"
0'
b1 (
#67000
1"
1'
#68000
0"
0'
b1 (
#69000
1"
1'
#70000
b110 !
0"
b100 $
b110 %
0'
b100 (
#71000
1"
1'
#72000
0"
0'
b100 (
#73000
1"
1'
#74000
0"
0'
b100 (
#75000
1"
1'
#76000
0"
0'
b100 (
#77000
1"
1'
#78000
0"
0'
b100 (
#79000
1"
1'
#80000
b111 !
0"
b1 $
b111 %
0'
b1 (
#81000
1"
1'
#82000
0"
0'
b1 (
#83000
1"
1'
#84000
0"
0'
b1 (
#85000
1"
1'
#86000
0"
0'
b1 (
#87000
1"
1'
#88000
0"
0'
b1 (
#89000
1"
1'
#90000
0"
0'
b1 (
#91000
1"
1'
#92000
0"
0'
b1 (
#93000
1"
1'
#94000
0"
0'
b1 (
#95000
1"
1'
#96000
0"
0'
b1 (
#97000
1"
1'
#98000
0"
0'
b1 (
